wsfactory/__init__.py
wsfactory/_helpers.py
wsfactory/config.py
wsfactory/urls.py
wsfactory/utils.py
wsfactory/views.py
wsfactory/management/__init__.py
wsfactory/management/commands/__init__.py
wsfactory/management/commands/wsfactory_default_config.py
wsfactory/management/commands/wsfactory_reload.py
wsfactory/schema/base_config.xml
wsfactory/schema/wsfactory.xsd
wsfactory-0.6.0.dist-info/licenses/LICENSE
wsfactory-0.6.0.dist-info/METADATA
wsfactory-0.6.0.dist-info/WHEEL
wsfactory-0.6.0.dist-info/dependency_links.txt
wsfactory-0.6.0.dist-info/top_level.txt
wsfactory-0.6.0.dist-info/RECORD
