Metadata-Version: 2.4
Name: wsfactory
Version: 0.6.0
Summary: О проекте
Home-page: https://stash.bars-open.ru/projects/M3/repos/wsfactory
Author: Timur Salyakhutdinov
Author-email: t.salyakhutdinov@gmail.com
License: Copyright © 2014 ЗАО “БАРС Груп”
Classifier: Intended Audience :: Developers
Classifier: Operating System :: OS Independent
Classifier: Programming Language :: Python
Classifier: Development Status :: 5 - Production/Stable
Classifier: Programming Language :: Python
Classifier: Programming Language :: Python :: 3.6
Classifier: Programming Language :: Python :: 3.7
Classifier: Framework :: Django :: 1.11
Classifier: Framework :: Django :: 2.0
Classifier: Framework :: Django :: 2.1
Classifier: Framework :: Django :: 2.2
Classifier: Framework :: Django :: 3.0
Classifier: Framework :: Django :: 3.1
Classifier: Framework :: Django :: 3.2
Classifier: Framework :: Django :: 4.0
License-File: LICENSE
Requires-Dist: lxml
Requires-Dist: requests
Requires-Dist: django<5.0,>=1.4
Requires-Dist: spyne
Dynamic: author
Dynamic: author-email
Dynamic: classifier
Dynamic: home-page
Dynamic: license
Dynamic: license-file
Dynamic: requires-dist
Dynamic: summary
